cht_utils/__init__.py
cht_utils/colors.py
cht_utils/deltares_ini.py
cht_utils/fileio.py
cht_utils/fileops.py
cht_utils/geometry.py
cht_utils/interpolation.py
cht_utils/misc_tools.py
cht_utils/pli_file.py
cht_utils/prob_maps.py
cht_utils/sftp.py
cht_utils/snapwave_mesh.py
cht_utils/tekal.py
cht_utils/watersheds.py
cht_utils/xmlkit.py
cht_utils-1.0.0.dist-info/LICENSE
cht_utils-1.0.0.dist-info/METADATA
cht_utils-1.0.0.dist-info/WHEEL
cht_utils-1.0.0.dist-info/top_level.txt
cht_utils-1.0.0.dist-info/RECORD
